<?xml version="1.0" encoding="utf-8"?>
<ATCTroops>
  <source_troop id="sturgian_recruit">
    <target_troop id="chael_nadra_recruit_f" percent="20" playeronly="true" AIonly="false" cultureonly="false" kingdomonly="false" />
    <target_troop id="chael_nadra_recruit_m" percent="20" playeronly="true" AIonly="false" cultureonly="false" kingdomonly="false" />
  </source_troop>
  <source_troop id="battanian_volunteer">
    <target_troop id="chael_nadra_recruit_f" percent="20" playeronly="true" AIonly="false" cultureonly="false" kingdomonly="false" />
    <target_troop id="chael_nadra_recruit_m" percent="20" playeronly="true" AIonly="false" cultureonly="false" kingdomonly="false" />
  </source_troop>
  <source_troop id="imperial_vigla_recruit">
    <target_troop id="chael_nadra_recruit_f" percent="5" playeronly="true" AIonly="false" cultureonly="false" kingdomonly="true" />
    <target_troop id="chael_nadra_recruit_m" percent="5" playeronly="true" AIonly="false" cultureonly="false" kingdomonly="true" />
  </source_troop>
  <source_troop id="vlandian_recruit">
    <target_troop id="chael_nadra_recruit_f" percent="20" playeronly="true" AIonly="false" cultureonly="false" kingdomonly="false" />
    <target_troop id="chael_nadra_recruit_m" percent="20" playeronly="true" AIonly="false" cultureonly="false" kingdomonly="false" />
  </source_troop>
  <source_troop id="imperial_recruit">
    <target_troop id="ere_recruit" percent="33" playeronly="true" AIonly="false" cultureonly="false" kingdomonly="false" />
    <target_troop id="chael_nadra_recruit_f" percent="33" playeronly="true" AIonly="false" cultureonly="false" kingdomonly="false" />
    <target_troop id="chael_nadra_recruit_m" percent="33" playeronly="true" AIonly="false" cultureonly="false" kingdomonly="false" />
  </source_troop>
</ATCTroops>